django_gui/__init__.py
django_gui/waitress/__init__.py
django_gui/waitress/__main__.py
django_gui/waitress/adjustments.py
django_gui/waitress/buffers.py
django_gui/waitress/channel.py
django_gui/waitress/compat.py
django_gui/waitress/parser.py
django_gui/waitress/proxy_headers.py
django_gui/waitress/receiver.py
django_gui/waitress/rfc7230.py
django_gui/waitress/runner.py
django_gui/waitress/server.py
django_gui/waitress/task.py
django_gui/waitress/trigger.py
django_gui/waitress/utilities.py
django_gui/waitress/wasyncore.py
django_gui/whitenoise/__init__.py
django_gui/whitenoise/base.py
django_gui/whitenoise/compress.py
django_gui/whitenoise/media_types.py
django_gui/whitenoise/middleware.py
django_gui/whitenoise/responders.py
django_gui/whitenoise/storage.py
django_gui/whitenoise/string_utils.py
django_gui/whitenoise/runserver_nostatic/__init__.py
django_gui/whitenoise/runserver_nostatic/management/__init__.py
django_gui/whitenoise/runserver_nostatic/management/commands/__init__.py
django_gui/whitenoise/runserver_nostatic/management/commands/runserver.py
django_gui-1.2.dist-info/LICENSE.txt
django_gui-1.2.dist-info/METADATA
django_gui-1.2.dist-info/WHEEL
django_gui-1.2.dist-info/top_level.txt
django_gui-1.2.dist-info/RECORD
