Metadata-Version: 2.2
Name: django_gui
Version: 1.2
Summary: Open Django project as desktop application!
Author: nekogen
Author-email: neko.gen@gmail.com
License: MIT
Requires-Python: >=3.10
License-File: LICENSE.txt
Requires-Dist: psutil
Dynamic: author
Dynamic: author-email
Dynamic: description
Dynamic: description-content-type
Dynamic: license
Dynamic: requires-dist
Dynamic: requires-python
Dynamic: summary
